usercfgopt/__init__.py
usercfg_opt_parser-1.0.0.dist-info/LICENSE
usercfg_opt_parser-1.0.0.dist-info/METADATA
usercfg_opt_parser-1.0.0.dist-info/WHEEL
usercfg_opt_parser-1.0.0.dist-info/RECORD
