Metadata-Version: 2.1
Name: usercfg-opt-parser
Version: 1.0.0
Summary: Parse Microsoft Flight Simulator UserCfg.opt files
Home-page: https://github.com/NathanVaughn/usercfg-opt-parser
License: MIT
Author: Nathan Vaughn
Author-email: nvaughn51@gmail.com
Requires-Python: >=3.9,<4.0
Classifier: License :: OSI Approved :: MIT License
Classifier: Programming Language :: Python :: 3
Classifier: Programming Language :: Python :: 3.9
Classifier: Programming Language :: Python :: 3.10
Classifier: Programming Language :: Python :: 3.11
Classifier: Programming Language :: Python :: 3.12
Requires-Dist: lark (>=1.1.9,<2.0.0)
Project-URL: Issues, https://github.com/NathanVaughn/usercfg-opt-parser/issues
Project-URL: Repository, https://github.com/NathanVaughn/usercfg-opt-parser.git
